pomoglorbo/__init__.py
pomoglorbo/b15.wav
pomoglorbo/b15.wav.license
pomoglorbo/cli.py
pomoglorbo/config.py
pomoglorbo/ipc.py
pomoglorbo/tomato.py
pomoglorbo/types.py
pomoglorbo/util.py
pomoglorbo/messages/__init__.py
pomoglorbo/messages/pomoglorbo.pot
pomoglorbo/messages/de/LC_MESSAGES/messages.mo
pomoglorbo/messages/de/LC_MESSAGES/messages.mo.license
pomoglorbo/messages/de/LC_MESSAGES/messages.po
pomoglorbo/messages/ja/LC_MESSAGES/messages.mo
pomoglorbo/messages/ja/LC_MESSAGES/messages.mo.license
pomoglorbo/messages/ja/LC_MESSAGES/messages.po
pomoglorbo/xdg_base_dirs/__init__.py
pomoglorbo-2025.8.21.dist-info/METADATA
pomoglorbo-2025.8.21.dist-info/WHEEL
pomoglorbo-2025.8.21.dist-info/entry_points.txt
pomoglorbo-2025.8.21.dist-info/RECORD
