Metadata-Version: 2.4
Name: pomoglorbo
Version: 2025.8.21
Summary: Terminal Pomodoro timer
Project-URL: Repository, https://codeberg.org/justusw/Pomoglorbo
Author-email: Bhathiya Perera <jadogg.coder@gmail.com>, Justus Perlwitz <justus@jwpconsulting.net>
Maintainer-email: Justus Perlwitz <justus@jwpconsulting.net>
License-Expression: MIT
Keywords: pomodoro,pomoglorbo,pydoro,timer,tomato,work
Classifier: License :: OSI Approved :: MIT License
Classifier: Programming Language :: Python :: 3
Classifier: Topic :: Office/Business :: Scheduling
Classifier: Topic :: Utilities
Requires-Python: ~=3.11
Requires-Dist: playsound3<4,>=3
Requires-Dist: prompt-toolkit<3.1,>=3.0
